{
  "model": "OI",
  "ticker": "QQQ",
  "spot": 720.73,
  "expirations_used": [
    "2026-05-22",
    "2026-05-26",
    "2026-05-27"
  ],
  "weights_used": [
    0.5,
    0.3,
    0.2
  ],
  "search_range": [
    690.73,
    750.73
  ],
  "key_level": 721.0,
  "top_resistances": [
    {
      "strike": 721.0,
      "weighted_open_interest": 2358.3,
      "total_open_interest": 5324,
      "weighted_volume": 57121.8,
      "total_volume": 117536.0
    },
    {
      "strike": 722.0,
      "weighted_open_interest": 5976.2,
      "total_open_interest": 13377,
      "weighted_volume": 48230.5,
      "total_volume": 100064.0
    },
    {
      "strike": 724.0,
      "weighted_open_interest": 2374.5,
      "total_open_interest": 7124,
      "weighted_volume": 37247.0,
      "total_volume": 75810.0
    },
    {
      "strike": 725.0,
      "weighted_open_interest": 5805.9,
      "total_open_interest": 13815,
      "weighted_volume": 30525.3,
      "total_volume": 64110.0
    },
    {
      "strike": 726.0,
      "weighted_open_interest": 1489.1,
      "total_open_interest": 3239,
      "weighted_volume": 16958.6,
      "total_volume": 35267.0
    },
    {
      "strike": 727.0,
      "weighted_open_interest": 1530.6,
      "total_open_interest": 3429,
      "weighted_volume": 8672.6,
      "total_volume": 18279.0
    },
    {
      "strike": 728.0,
      "weighted_open_interest": 1464.2,
      "total_open_interest": 3530,
      "weighted_volume": 5166.5,
      "total_volume": 11324.0
    },
    {
      "strike": 730.0,
      "weighted_open_interest": 9032.2,
      "total_open_interest": 19170,
      "weighted_volume": 8242.8,
      "total_volume": 17695.0
    },
    {
      "strike": 731.0,
      "weighted_open_interest": 1573.6,
      "total_open_interest": 3455,
      "weighted_volume": 3138.6,
      "total_volume": 6859.0
    },
    {
      "strike": 732.0,
      "weighted_open_interest": 1439.7,
      "total_open_interest": 3083,
      "weighted_volume": 3410.4,
      "total_volume": 7644.0
    },
    {
      "strike": 734.0,
      "weighted_open_interest": 1433.3,
      "total_open_interest": 3726,
      "weighted_volume": 5830.6,
      "total_volume": 12106.0
    },
    {
      "strike": 735.0,
      "weighted_open_interest": 3161.0,
      "total_open_interest": 6936,
      "weighted_volume": 2257.3,
      "total_volume": 5756.0
    },
    {
      "strike": 740.0,
      "weighted_open_interest": 3676.1,
      "total_open_interest": 8060,
      "weighted_volume": 1836.8,
      "total_volume": 4595.0
    },
    {
      "strike": 745.0,
      "weighted_open_interest": 1420.5,
      "total_open_interest": 3260,
      "weighted_volume": 376.3,
      "total_volume": 1160.0
    },
    {
      "strike": 750.0,
      "weighted_open_interest": 3607.4,
      "total_open_interest": 7911,
      "weighted_volume": 169.20000000000002,
      "total_volume": 567.0
    }
  ],
  "top_supports": [
    {
      "strike": 715.0,
      "weighted_open_interest": 3225.2,
      "total_open_interest": 7130,
      "weighted_volume": 29679.8,
      "total_volume": 63632.0
    },
    {
      "strike": 712.0,
      "weighted_open_interest": 2694.6,
      "total_open_interest": 5939,
      "weighted_volume": 13313.8,
      "total_volume": 28830.0
    },
    {
      "strike": 711.0,
      "weighted_open_interest": 2602.5,
      "total_open_interest": 5901,
      "weighted_volume": 10845.4,
      "total_volume": 22715.0
    },
    {
      "strike": 710.0,
      "weighted_open_interest": 7130.5,
      "total_open_interest": 17058,
      "weighted_volume": 14113.4,
      "total_volume": 31609.0
    },
    {
      "strike": 709.0,
      "weighted_open_interest": 2656.4,
      "total_open_interest": 6359,
      "weighted_volume": 7255.3,
      "total_volume": 15333.0
    },
    {
      "strike": 708.0,
      "weighted_open_interest": 2803.4,
      "total_open_interest": 6322,
      "weighted_volume": 4665.4,
      "total_volume": 10112.0
    },
    {
      "strike": 707.0,
      "weighted_open_interest": 2618.0,
      "total_open_interest": 5838,
      "weighted_volume": 6011.0,
      "total_volume": 12807.0
    },
    {
      "strike": 705.0,
      "weighted_open_interest": 10009.0,
      "total_open_interest": 21594,
      "weighted_volume": 7532.599999999999,
      "total_volume": 17892.0
    },
    {
      "strike": 703.0,
      "weighted_open_interest": 2639.5,
      "total_open_interest": 6010,
      "weighted_volume": 4417.9,
      "total_volume": 9175.0
    },
    {
      "strike": 702.0,
      "weighted_open_interest": 3318.2,
      "total_open_interest": 7742,
      "weighted_volume": 2095.6,
      "total_volume": 4809.0
    },
    {
      "strike": 700.0,
      "weighted_open_interest": 9703.0,
      "total_open_interest": 22257,
      "weighted_volume": 3918.9,
      "total_volume": 9218.0
    },
    {
      "strike": 698.0,
      "weighted_open_interest": 2493.6,
      "total_open_interest": 5647,
      "weighted_volume": 3118.7,
      "total_volume": 6866.0
    },
    {
      "strike": 696.0,
      "weighted_open_interest": 2269.5,
      "total_open_interest": 4974,
      "weighted_volume": 1950.0,
      "total_volume": 4255.0
    },
    {
      "strike": 695.0,
      "weighted_open_interest": 4749.9,
      "total_open_interest": 11143,
      "weighted_volume": 2733.9,
      "total_volume": 6308.0
    },
    {
      "strike": 694.0,
      "weighted_open_interest": 2926.4,
      "total_open_interest": 6580,
      "weighted_volume": 1739.5,
      "total_volume": 3875.0
    }
  ],
  "refreshed_at_ny": "2026-05-22T12:03:19.706934-04:00"
}