{
  "model": "OI",
  "ticker": "SPY",
  "spot": 712.56,
  "expirations_used": [
    "2026-04-27",
    "2026-04-28",
    "2026-04-29"
  ],
  "weights_used": [
    0.5,
    0.3,
    0.2
  ],
  "search_range": [
    682.56,
    742.56
  ],
  "key_level": 713.0,
  "top_resistances": [
    {
      "strike": 713.0,
      "weighted_open_interest": 4045.6,
      "total_open_interest": 9572,
      "weighted_volume": 67875.8,
      "total_volume": 141899.0
    },
    {
      "strike": 714.0,
      "weighted_open_interest": 5137.9,
      "total_open_interest": 12179,
      "weighted_volume": 102895.5,
      "total_volume": 215608.0
    },
    {
      "strike": 715.0,
      "weighted_open_interest": 4629.8,
      "total_open_interest": 11704,
      "weighted_volume": 93364.5,
      "total_volume": 193969.0
    },
    {
      "strike": 716.0,
      "weighted_open_interest": 6458.2,
      "total_open_interest": 14278,
      "weighted_volume": 43803.9,
      "total_volume": 91871.0
    },
    {
      "strike": 717.0,
      "weighted_open_interest": 3438.3,
      "total_open_interest": 8546,
      "weighted_volume": 24549.2,
      "total_volume": 52154.0
    },
    {
      "strike": 718.0,
      "weighted_open_interest": 3511.6,
      "total_open_interest": 8875,
      "weighted_volume": 16520.5,
      "total_volume": 35662.0
    },
    {
      "strike": 719.0,
      "weighted_open_interest": 3592.9,
      "total_open_interest": 8795,
      "weighted_volume": 17447.5,
      "total_volume": 37260.0
    },
    {
      "strike": 720.0,
      "weighted_open_interest": 19169.3,
      "total_open_interest": 42278,
      "weighted_volume": 14881.6,
      "total_volume": 32410.0
    },
    {
      "strike": 722.0,
      "weighted_open_interest": 4545.9,
      "total_open_interest": 10668,
      "weighted_volume": 3963.5,
      "total_volume": 9512.0
    },
    {
      "strike": 723.0,
      "weighted_open_interest": 3323.2999999999997,
      "total_open_interest": 7868,
      "weighted_volume": 2338.6,
      "total_volume": 5469.0
    },
    {
      "strike": 724.0,
      "weighted_open_interest": 3458.2,
      "total_open_interest": 8455,
      "weighted_volume": 697.8,
      "total_volume": 1864.0
    },
    {
      "strike": 725.0,
      "weighted_open_interest": 7211.2,
      "total_open_interest": 17141,
      "weighted_volume": 1378.1,
      "total_volume": 3903.0
    },
    {
      "strike": 730.0,
      "weighted_open_interest": 3497.1,
      "total_open_interest": 9342,
      "weighted_volume": 730.4,
      "total_volume": 1862.0
    },
    {
      "strike": 735.0,
      "weighted_open_interest": 3606.5,
      "total_open_interest": 9220,
      "weighted_volume": 125.3,
      "total_volume": 280.0
    },
    {
      "strike": 736.0,
      "weighted_open_interest": 4183.3,
      "total_open_interest": 11224,
      "weighted_volume": 240.4,
      "total_volume": 688.0
    }
  ],
  "top_supports": [
    {
      "strike": 712.0,
      "weighted_open_interest": 12053.4,
      "total_open_interest": 25334.0,
      "weighted_volume": 101635.4,
      "total_volume": 209496.0
    },
    {
      "strike": 711.0,
      "weighted_open_interest": 6637.5,
      "total_open_interest": 15428.0,
      "weighted_volume": 45187.9,
      "total_volume": 96383.0
    },
    {
      "strike": 710.0,
      "weighted_open_interest": 6586.8,
      "total_open_interest": 16090.0,
      "weighted_volume": 41106.9,
      "total_volume": 86928.0
    },
    {
      "strike": 709.0,
      "weighted_open_interest": 4245.0,
      "total_open_interest": 10120.0,
      "weighted_volume": 23140.0,
      "total_volume": 48231.0
    },
    {
      "strike": 708.0,
      "weighted_open_interest": 5655.9,
      "total_open_interest": 15384.0,
      "weighted_volume": 15460.3,
      "total_volume": 35467.0
    },
    {
      "strike": 707.0,
      "weighted_open_interest": 5492.4,
      "total_open_interest": 13360.0,
      "weighted_volume": 12673.5,
      "total_volume": 28089.0
    },
    {
      "strike": 705.0,
      "weighted_open_interest": 8650.4,
      "total_open_interest": 20827.0,
      "weighted_volume": 16349.7,
      "total_volume": 34411.0
    },
    {
      "strike": 703.0,
      "weighted_open_interest": 4300.6,
      "total_open_interest": 10602.0,
      "weighted_volume": 14228.8,
      "total_volume": 32247.0
    },
    {
      "strike": 700.0,
      "weighted_open_interest": 11920.9,
      "total_open_interest": 28805.0,
      "weighted_volume": 10143.6,
      "total_volume": 25815.0
    },
    {
      "strike": 699.0,
      "weighted_open_interest": 4488.9,
      "total_open_interest": 9724.0,
      "weighted_volume": 2707.7,
      "total_volume": 6078.0
    },
    {
      "strike": 697.0,
      "weighted_open_interest": 4447.8,
      "total_open_interest": 11739.0,
      "weighted_volume": 2101.4,
      "total_volume": 4750.0
    },
    {
      "strike": 695.0,
      "weighted_open_interest": 7602.7,
      "total_open_interest": 17940.0,
      "weighted_volume": 3342.2,
      "total_volume": 8056.0
    },
    {
      "strike": 690.0,
      "weighted_open_interest": 11070.3,
      "total_open_interest": 24977.0,
      "weighted_volume": 1178.5,
      "total_volume": 3304.0
    },
    {
      "strike": 687.0,
      "weighted_open_interest": 4186.6,
      "total_open_interest": 9257.0,
      "weighted_volume": 600.2,
      "total_volume": 1387.0
    },
    {
      "strike": 685.0,
      "weighted_open_interest": 15860.0,
      "total_open_interest": 48535.0,
      "weighted_volume": 1158.5,
      "total_volume": 2856.0
    }
  ],
  "refreshed_at_ny": "2026-04-27T11:25:22.448968-04:00"
}